pxrd/__init__.py
pxrd/convert.py
pxrd/keywords.py
pxrd/px2csv.py
pxrd/pxread.py
pxrd-0.0.3.dist-info/LICENSE
pxrd-0.0.3.dist-info/METADATA
pxrd-0.0.3.dist-info/WHEEL
pxrd-0.0.3.dist-info/entry_points.txt
pxrd-0.0.3.dist-info/top_level.txt
pxrd-0.0.3.dist-info/RECORD
