Metadata-Version: 2.1
Name: pxrd
Version: 0.0.3
Summary: PC-Axis PX file reader
Home-page: https://github.com/murci/pxrd
Author: Asier Murciego Alonso
Author-email: asier.murciego@deusto.es
License: UNKNOWN
Keywords: pcaxis,px
Platform: UNKNOWN
Classifier: Programming Language :: Python :: 3
Classifier: Programming Language :: Python :: 3.6
Classifier: Programming Language :: Python :: 3.7
Classifier: Programming Language :: Python :: 3.8
Classifier: Programming Language :: Python :: 3.9
Classifier: Programming Language :: Python :: 3 :: Only
Classifier: Operating System :: OS Independent
Classifier: Topic :: Software Development :: Libraries :: Python Modules
Requires-Python: >=3.6
License-File: LICENSE
